andoya/core/__init__.py
andoya/core/exceptions.py
andoya/core/manifest.py
andoya/core/stubs/__init__.py
andoya/core/stubs/cli_handler.stub.py
andoya/core/stubs/http_handler.stub.py
andoya/core/stubs/rds_ca_cert.pem
andoya/core/toml.py
andoya_core-0.1.0.dist-info/WHEEL
andoya_core-0.1.0.dist-info/METADATA
andoya_core-0.1.0.dist-info/RECORD
