Metadata-Version: 2.1
Name: andoya-core
Version: 0.1.0
Summary: The Andoya Core package.
Author: Ian Rodrigues
Author-email: ianrdgs@gmail.com
Requires-Python: >=3.8,<4.0
Classifier: Programming Language :: Python :: 3
Classifier: Programming Language :: Python :: 3.10
Classifier: Programming Language :: Python :: 3.8
Classifier: Programming Language :: Python :: 3.9
Requires-Dist: tomlkit (>=0.8.0,<0.9.0)
